MANIFEST.in
README.md
setup.py
mural/Business.py
mural/Commodity.py
mural/Convoy.py
mural/Market.py
mural/Profile.py
mural/Saveable.py
mural/Trader.py
mural/__init__.py
mural/build.py
mural/db.py
mural/db_build.py
mural/driver.py
mural/example_business.py
mural/oracle.yaml
mural/test.py
mural.egg-info/PKG-INFO
mural.egg-info/SOURCES.txt
mural.egg-info/dependency_links.txt
mural.egg-info/requires.txt
mural.egg-info/top_level.txt
mural/bin/business
mural/bin/convoy
mural/bin/market
mural/bin/me
mural/bin/mine
mural/bin/net
mural/bin/new_account
mural/bin/oracle
mural/bin/setAccount
mural/bin/transact
mural/bin/update
mural/static/base.css
mural/static/canvas.css
mural/static/canvas.js
mural/static/jquery.js
mural/templates/canvas.html
mural/templates/index.html
mural/templates/market.html