Metadata-Version: 2.1
Name: mural
Version: 0.0.24
Summary: Market game
Home-page: https://github.com/Tsangares/market
Author: William Wyatt
Author-email: wwyatt@ucsc.edu
License: UNKNOWN
Platform: UNKNOWN
Classifier: Programming Language :: Python :: 3
Classifier: License :: OSI Approved :: MIT License
